{
  "table_id": "page_51_table_28",
  "page_number": 51,
  "original_table_html": "<table>\n<thead>\n<tr>\n<th>Times Pepsi Bought</th>\n<th>Percentage of Cola Buyers Buying Pepsi</th>\n</tr>\n</thead>\n<tbody>\n<tr><td>0</td><td>50</td></tr>\n<tr><td>1</td><td>12</td></tr>\n<tr><td>2</td><td>8</td></tr>\n<tr><td>3</td><td>5</td></tr>\n<tr><td>4</td><td>3</td></tr>\n<tr><td>5</td><td>2</td></tr>\n<tr><td>6</td><td>1.5</td></tr>\n<tr><td>7</td><td>1</td></tr>\n<tr><td>8</td><td>0.8</td></tr>\n<tr><td>9</td><td>0.7</td></tr>\n<tr><td>10</td><td>0.5</td></tr>\n<tr><td>11</td><td>0.4</td></tr>\n<tr><td>12</td><td>0.3</td></tr>\n<tr><td>13</td><td>0.3</td></tr>\n<tr><td>14</td><td>0.2</td></tr>\n<tr><td>15</td><td>0.2</td></tr>\n<tr><td>16</td><td>0.1</td></tr>\n<tr><td>17</td><td>0.1</td></tr>\n<tr><td>18</td><td>0.1</td></tr>\n<tr><td>19</td><td>0.1</td></tr>\n<tr><td>20</td><td>0.1</td></tr>\n<tr><td>21</td><td>0.05</td></tr>\n<tr><td>22</td><td>0.05</td></tr>\n<tr><td>23</td><td>0.05</td></tr>\n<tr><td>24</td><td>0.05</td></tr>\n<tr><td>25</td><td>0.05</td></tr>\n<tr><td>26</td><td>0.05</td></tr>\n<tr><td>27</td><td>0.05</td></tr>\n<tr><td>28</td><td>0.05</td></tr>\n<tr><td>29</td><td>0.05</td></tr>\n<tr><td>30</td><td>0.05</td></tr>\n<tr><td>31</td><td>0.05</td></tr>\n<tr><td>32</td><td>0.05</td></tr>\n<tr><td>33</td><td>0.05</td></tr>\n<tr><td>34</td><td>0.05</td></tr>\n<tr><td>35</td><td>0.05</td></tr>\n<tr><td>36</td><td>0.05</td></tr>\n<tr><td>37</td><td>0.05</td></tr>\n<tr><td>38</td><td>0.05</td></tr>\n<tr><td>39</td><td>0.05</td></tr>\n<tr><td>40</td><td>0.05</td></tr>\n<tr><td>41</td><td>0.05</td></tr>\n<tr><td>42</td><td>0.05</td></tr>\n<tr><td>43</td><td>0.05</td></tr>\n<tr><td>44</td><td>0.05</td></tr>\n<tr><td>45</td><td>0.05</td></tr>\n<tr><td>46</td><td>0.05</td></tr>\n<tr><td>47</td><td>0.05</td></tr>\n<tr><td>48</td><td>0.05</td></tr>\n<tr><td>49</td><td>0.05</td></tr>\n<tr><td>50</td><td>0.05</td></tr>\n<tr><td>51</td><td>0.05</td></tr>\n<tr><td>52</td><td>0.05</td></tr>\n</tbody>\n</table>",
  "summary_markdown": "This data presents a comparative analysis of Pepsi purchase frequency and its correlation with the percentage of cola buyers. Initially, when Pepsi is bought 0 times, 50% of cola buyers purchase it. As the number of times Pepsi is bought increases, the percentage of cola buyers purchasing Pepsi shows a sharp decline. For instance, at 1 purchase, this figure drops to 12%, and further decreases to 8% at 2 purchases, and 5% at 3 purchases. This downward trend continues, with the percentage of cola buyers steadily decreasing as purchase frequency rises. By 10 purchases, the percentage is 0.5%, and it reaches 0.1% by 16 purchases. Beyond 20 purchases, the percentage stabilizes at a low of 0.05%, remaining constant up to 52 purchases, indicating a diminishing impact of higher purchase frequencies on the overall proportion of cola buyers.",
  "processing_time": 1.5101287364959717,
  "was_merged": false,
  "source_chain_id": null,
  "timestamp": "2026-02-06T17:20:38.297481"
}