{
  "table_id": "page_66_table_39",
  "page_number": 66,
  "original_table_html": "<table><thead><tr><th>Category</th><th>Demo</th><th>Media</th><th>Values</th><th>Average</th></tr></thead><tbody><tr><td>Cigarettes</td><td>4</td><td>4</td><td>6</td><td>6</td></tr><tr><td>Cat food</td><td>3</td><td>1</td><td>4</td><td>4</td></tr><tr><td>Mints</td><td>3</td><td>1</td><td>3</td><td>3</td></tr><tr><td>Toothbrushes</td><td>3</td><td>1</td><td>3</td><td>3</td></tr><tr><td>Private health insurance</td><td>4</td><td>2</td><td>3</td><td>3</td></tr><tr><td>Sweets</td><td>3</td><td>1</td><td>2</td><td>3</td></tr><tr><td>Crisps</td><td>3</td><td>1</td><td>3</td><td>3</td></tr><tr><td>Toilet soap</td><td>3</td><td>1</td><td>2</td><td>3</td></tr><tr><td>Package holidays</td><td>3</td><td>1</td><td>3</td><td>3</td></tr><tr><td>Dry batteries</td><td>3</td><td>1</td><td>2</td><td>3</td></tr><tr><td>Other chocolate</td><td>3</td><td>1</td><td>2</td><td>2</td></tr><tr><td>Kitchen rolls</td><td>3</td><td>1</td><td>3</td><td>2</td></tr><tr><td>Nuts</td><td>3</td><td>1</td><td>2</td><td>2</td></tr><tr><td>Chocolate bars</td><td>3</td><td>1</td><td>2</td><td>2</td></tr><tr><td>Toothpaste</td><td>2</td><td>1</td><td>2</td><td>2</td></tr><tr><td>Toilet paper</td><td>2</td><td>1</td><td>2</td><td>2</td></tr><tr><td>Computers</td><td>3</td><td>2</td><td>2</td><td>2</td></tr><tr><td>Record shops</td><td>3</td><td>1</td><td>1</td><td>2</td></tr><tr><td>Store retail cards</td><td>3</td><td>1</td><td>2</td><td>2</td></tr><tr><td>Computer games</td><td>3</td><td>1</td><td>2</td><td>2</td></tr><tr><td>Vitamins</td><td>3</td><td>1</td><td>2</td><td>2</td></tr><tr><td>Liquid detergent</td><td>3</td><td>1</td><td>2</td><td>2</td></tr><tr><td>Grocers</td><td>3</td><td>1</td><td>2</td><td>2</td></tr><tr><td>Yogurt</td><td>3</td><td>1</td><td>2</td><td>2</td></tr><tr><td>Light bulbs</td><td>2</td><td>1</td><td>2</td><td>2</td></tr><tr><td>Car tyres</td><td>2</td><td>1</td><td>2</td><td>2</td></tr><tr><td>Stain removers</td><td>2</td><td>1</td><td>2</td><td>2</td></tr><tr><td>Car insurance</td><td>3</td><td>1</td><td>1</td><td>2</td></tr><tr><td>Coffee</td><td>2</td><td>1</td><td>2</td><td>2</td></tr><tr><td>Home contents</td><td>2</td><td>1</td><td>1</td><td>2</td></tr><tr><td>Paint</td><td>3</td><td>1</td><td>1</td><td>2</td></tr><tr><td>Shampoo</td><td>2</td><td>1</td><td>2</td><td>2</td></tr><tr><td>Airlines</td><td>2</td><td>1</td><td>1</td><td>1</td></tr><tr><td>Camera film</td><td>2</td><td>1</td><td>1</td><td>1</td></tr><tr><td>Headache tablets</td><td>2</td><td>1</td><td>1</td><td>1</td></tr><tr><td>Cars</td><td>2</td><td>1</td><td>1</td><td>1</td></tr><tr><td>Credit cards</td><td>2</td><td>1</td><td>1</td><td>1</td></tr><tr><td>Mortgages</td><td>2</td><td>1</td><td>1</td><td>1</td></tr><tr><td>Fuel</td><td>2</td><td>1</td><td>1</td><td>1</td></tr><tr><td>Retailers</td><td>1</td><td>1</td><td>1</td><td>1</td></tr><tr><td>Average</td><td>3</td><td>1</td><td>2</td><td>2</td></tr></tbody></table>",
  "summary_markdown": "This data presents a comparative analysis of product categories across three metrics: Demo, Media, and Values, culminating in an Average score. The structure is a simple enumeration of product categories, each assigned numerical values for these metrics. The categories are diverse, ranging from everyday consumables like \"Cigarettes\" and \"Cat food\" to services such as \"Private health insurance\" and \"Package holidays,\" and even durable goods like \"Computers\" and \"Cars.\" The values assigned appear to represent some form of rating or frequency, with higher numbers indicating a greater presence or significance within each metric. The \"Average\" column aggregates these scores, providing a consolidated measure for each category. Notably, \"Cigarettes\" stands out with the highest scores across all metrics and the overall average, while categories like \"Airlines,\" \"Camera film,\" and \"Cars\" consistently receive lower scores. The table concludes with an overall average across all categories for each metric, serving as a benchmark.",
  "processing_time": 1.08793306350708,
  "was_merged": true,
  "source_chain_id": "page_66_chain_6_cross",
  "timestamp": "2026-02-06T17:20:38.298656"
}