{
  "table_id": "page_336_table_73",
  "page_number": 336,
  "original_table_html": "<table>\n<thead>\n<tr>\n<th>Factors</th>\n<th>Sincerity</th>\n<th>Excitement</th>\n<th>Competence</th>\n<th>Sophistication</th>\n<th>Ruggedness</th>\n</tr>\n</thead>\n<tbody>\n<tr>\n<td>Facets</td>\n<td>Down-to-earth<br>Honest<br>Wholesome<br>Cheerful</td>\n<td>Daring<br>Spirited<br>Imaginative<br>Up-to-date</td>\n<td>Reliable<br>Intelligent<br>Successful</td>\n<td>Upper-class<br>Charming</td>\n<td>Outdoorsy<br>Tough</td>\n</tr>\n<tr>\n<td>Traits</td>\n<td>down-to-earth<br>family-oriented<br>small-town<br>honest<br>sincere<br>real</td>\n<td>wholesome<br>original<br>cheerful<br>sentimental<br>friendly</td>\n<td>daring<br>trendy<br>exciting<br>spirited<br>cool<br>young</td>\n<td>imaginative<br>unique<br>up-to-date<br>independent<br>contemporary</td>\n<td>reliable<br>hard-working<br>secure<br>intelligent<br>technical<br>corporate</td>\n<td>successful<br>leader<br>confident<br>charming<br>feminine<br>smooth</td>\n<td>tough<br>rugged<br>outdoorsy<br>masculine<br>western</td>\n</tr>\n</tbody>\n</table>",
  "summary_markdown": "This table outlines five core brand personality dimensions: Sincerity, Excitement, Competence, Sophistication, and Ruggedness. Each dimension is further broken down into specific facets and associated traits. Sincerity encompasses being down-to-earth, honest, wholesome, and cheerful, with traits like family-oriented and sincere. Excitement is characterized by daring, spirited, imaginative, and up-to-date facets, reflected in traits such as trendy, cool, and independent. Competence is defined by reliability, intelligence, and success, manifesting as hard-working, technical, and leader traits. Sophistication involves being upper-class and charming, with facets like charming and smooth. Finally, Ruggedness is associated with being outdoorsy and tough, evident in traits like masculine and western. This structure presents a hierarchical framework for understanding brand personality, moving from broad dimensions to specific descriptive traits.",
  "processing_time": 1.2928972244262695,
  "was_merged": false,
  "source_chain_id": null,
  "timestamp": "2026-02-06T16:56:11.273008"
}